get_ppbrowser/__init__.py
get_ppbrowser/config.py
get_ppbrowser/get_ppbrowser.py
get_ppbrowser-0.1.3.dist-info/WHEEL
get_ppbrowser-0.1.3.dist-info/METADATA
get_ppbrowser-0.1.3.dist-info/RECORD
