Metadata-Version: 2.1
Name: get-ppbrowser
Version: 0.1.3
Summary: Create a valid pyppeteer browser
Home-page: https://github.com/ffreemt/get-ppbrowser
License: MIT
Author: freemt
Requires-Python: >=3.7,<4.0
Classifier: License :: OSI Approved :: MIT License
Classifier: Programming Language :: Python :: 3
Classifier: Programming Language :: Python :: 3.7
Classifier: Programming Language :: Python :: 3.8
Classifier: Programming Language :: Python :: 3.9
Requires-Dist: logzero (>=1.6.3,<2.0.0)
Requires-Dist: pydantic (>=1.7.3,<2.0.0)
Requires-Dist: pyppeteer2 (>=0.2.2,<0.3.0)
Requires-Dist: pytest-asyncio (>=0.14.0,<0.15.0)
Requires-Dist: python-dotenv (>=0.15.0,<0.16.0)
Project-URL: Repository, https://github.com/ffreemt/get-ppbrowser
